<annotation>
	<folder>train</folder>
	<filename>scratch37.jpg</filename>
	<path>C:\Users\onury\Desktop\tensorflow\workspace\training_demo\images\train\scratch37.jpg</path>
	<source>
		<database>Unknown</database>
	</source>
	<size>
		<width>512</width>
		<height>512</height>
		<depth>1</depth>
	</size>
	<segmented>0</segmented>
	<object>
		<name>DefectTypeC</name>
		<pose>Unspecified</pose>
		<truncated>0</truncated>
		<difficult>0</difficult>
		<bndbox>
			<xmin>129</xmin>
			<ymin>281</ymin>
			<xmax>186</xmax>
			<ymax>337</ymax>
		</bndbox>
	</object>
</annotation>
